hatch_plugin.py
metadata.json
SecuredFiles/__init__.py
SecuredFiles/__main__.py
SecuredFiles/metadata.json
securedfiles-1.1.0.dist-info/METADATA
securedfiles-1.1.0.dist-info/WHEEL
securedfiles-1.1.0.dist-info/licenses/LICENSE
securedfiles-1.1.0.dist-info/RECORD
