Metadata-Version: 2.4
Name: SecuredFiles
Version: 1.1.0
Summary: Python's library for protect your files.
Project-URL: Homepage, https://github.com/LassaInora/SecuritedFiles
Project-URL: Repository, https://github.com/LassaInora/SecuredFiles.git
Project-URL: Issues, https://github.com/LassaInora/SecuritedFiles/issues
Author-email: LassaInora <contact@lassainora.fr>
License-Expression: GPL-3.0-or-later
License-File: LICENSE
Keywords: File,Files,Secured
Classifier: Development Status :: 6 - Mature
Classifier: Operating System :: OS Independent
Classifier: Programming Language :: Python
Classifier: Programming Language :: Python :: 3
Classifier: Programming Language :: Python :: 3 :: Only
Classifier: Programming Language :: Python :: 3.7
Classifier: Programming Language :: Python :: 3.8
Classifier: Programming Language :: Python :: 3.9
Classifier: Programming Language :: Python :: 3.10
Classifier: Programming Language :: Python :: 3.11
Classifier: Programming Language :: Python :: 3.12
Classifier: Programming Language :: Python :: 3.13
Classifier: Topic :: File Formats
Classifier: Topic :: Security :: Cryptography
Requires-Python: >=3.7
Requires-Dist: cryptography>=41.0.3
Requires-Dist: pyqt5
